boltwood_parser/__init__.py
boltwood_parser/collection.py
boltwood_parser/entry.py
boltwood_parser/flags.py
boltwood_parser/utils.py
boltwood_parser-0.1.0.dist-info/LICENSE
boltwood_parser-0.1.0.dist-info/METADATA
boltwood_parser-0.1.0.dist-info/WHEEL
boltwood_parser-0.1.0.dist-info/top_level.txt
boltwood_parser-0.1.0.dist-info/RECORD
