Metadata-Version: 2.1
Name: boltwood-parser
Version: 0.1.0
Summary: A library for parsing Boltwood II single line weather data.
Author-email: kinderhead <kinderhead512@gmail.com>
Project-URL: Homepage, https://github.com/kinderhead/boltwood-parser
Project-URL: Issues, https://github.com/kinderhead/boltwood-parser/issues
Classifier: Programming Language :: Python :: 3
Classifier: License :: OSI Approved :: MIT License
Classifier: Operating System :: OS Independent
Requires-Python: >=3.8
License-File: LICENSE
